funcnodes_lmfit/__init__.py
funcnodes_lmfit/_auto_model.py
funcnodes_lmfit/fitting.py
funcnodes_lmfit/model.py
funcnodes_lmfit/params.py
funcnodes_lmfit/plotting.py
funcnodes_lmfit/use_model.py
funcnodes_lmfit/utils.py
funcnodes_lmfit/__pycache__/__init__.cpython-312.pyc
funcnodes_lmfit/__pycache__/_auto_model.cpython-312.pyc
funcnodes_lmfit/__pycache__/fitting.cpython-312.pyc
funcnodes_lmfit/__pycache__/model.cpython-312.pyc
funcnodes_lmfit/__pycache__/params.cpython-312.pyc
funcnodes_lmfit/__pycache__/plotting.cpython-312.pyc
funcnodes_lmfit/__pycache__/use_model.cpython-312.pyc
funcnodes_lmfit/__pycache__/utils.cpython-312.pyc
funcnodes_lmfit-0.2.0.dist-info/LICENSE
funcnodes_lmfit-0.2.0.dist-info/METADATA
funcnodes_lmfit-0.2.0.dist-info/WHEEL
funcnodes_lmfit-0.2.0.dist-info/entry_points.txt
funcnodes_lmfit-0.2.0.dist-info/top_level.txt
funcnodes_lmfit-0.2.0.dist-info/RECORD
