Metadata-Version: 2.2
Name: funcnodes-lmfit
Version: 0.2.0
License: AGPL-3.0
Project-URL: homepage, https://github.com/Linkdlab/funcnodes_lmfit
Project-URL: source, https://github.com/Linkdlab/funcnodes_lmfit
Project-URL: tracker, https://github.com/Linkdlab/funcnodes_lmfit/issues
Project-URL: download, https://pypi.org/project/funcnodes-lmfit/#files
Requires-Python: >=3.11
License-File: LICENSE
Requires-Dist: funcnodes
Requires-Dist: lmfit
Requires-Dist: tqdm>=4.67.1
